repo_man/__init__.py
repo_man/cli.py
repo_man/consts.py
repo_man/py.typed
repo_man/utils.py
repo_man/commands/__init__.py
repo_man/commands/add.py
repo_man/commands/edit.py
repo_man/commands/implode.py
repo_man/commands/init.py
repo_man/commands/list_repos.py
repo_man/commands/remove.py
repo_man/commands/sniff.py
repo_man/commands/types.py
repo_man-0.1.2.dist-info/licenses/LICENSE
repo_man-0.1.2.dist-info/METADATA
repo_man-0.1.2.dist-info/WHEEL
repo_man-0.1.2.dist-info/entry_points.txt
repo_man-0.1.2.dist-info/top_level.txt
repo_man-0.1.2.dist-info/RECORD
