Metadata-Version: 2.4
Name: repo-man
Version: 0.1.2
Summary: Manage repositories of a variety of different types.
Author-email: Dane Hillard <github@danehillard.com>
Project-URL: Documentation, https://repo-man.readthedocs.org
Project-URL: Repository, https://github.com/easy-as-python/repo-man
Project-URL: Issues, https://github.com/easy-as-python/repo-man/issues
Classifier: Development Status :: 5 - Production/Stable
Classifier: Intended Audience :: Developers
Classifier: Programming Language :: Python
Classifier: Programming Language :: Python :: 3.10
Classifier: Programming Language :: Python :: 3.11
Classifier: Programming Language :: Python :: 3.12
Classifier: Programming Language :: Python :: 3.13
Classifier: Programming Language :: Python :: 3
Classifier: Programming Language :: Python :: 3 :: Only
Requires-Python: >=3.10
License-File: LICENSE
Requires-Dist: typer>=0.12.5
Provides-Extra: docs
Requires-Dist: furo; extra == "docs"
Requires-Dist: myst-parser; extra == "docs"
Requires-Dist: sphinx; extra == "docs"
Requires-Dist: sphinx-autobuild; extra == "docs"
Dynamic: license-file
